tracardi_sending_mail/__init__.py
tracardi_sending_mail/manual/README_sending_mail.md
tracardi_sending_mail/plugin/__init__.py
tracardi_sending_mail/plugin/sending_mail_via_gmail.py
tracardi_sending_mail/plugin/__pycache__/__init__.cpython-38.pyc
tracardi_sending_mail-0.2.1.dist-info/LICENSE.md
tracardi_sending_mail-0.2.1.dist-info/METADATA
tracardi_sending_mail-0.2.1.dist-info/WHEEL
tracardi_sending_mail-0.2.1.dist-info/top_level.txt
tracardi_sending_mail-0.2.1.dist-info/RECORD
