Metadata-Version: 2.1
Name: tracardi-sending-mail
Version: 0.2.1
Summary: The purpose of this plugin is sending mail with tracardi system.
Home-page: UNKNOWN
Author: Patryk Migaj
Author-email: patromi123@gmail.com
License: UNKNOWN
Keywords: tracardi,plugin
Platform: UNKNOWN
Classifier: Programming Language :: Python :: 3
Classifier: License :: OSI Approved :: MIT License
Classifier: Operating System :: OS Independent
Classifier: Development Status :: 3 - Alpha
Requires-Python: >=3.8
Requires-Dist: aiofiles (==0.7.0)
Requires-Dist: aiohttp (==3.7.4.post0)
Requires-Dist: asgiref (==3.4.1)
Requires-Dist: async-timeout (==3.0.1)
Requires-Dist: asyncio (==3.4.3)
Requires-Dist: attrs (==21.2.0)
Requires-Dist: certifi (==2021.5.30)
Requires-Dist: chardet (==4.0.0)
Requires-Dist: click (==8.0.1)
Requires-Dist: colorama (==0.4.4)
Requires-Dist: dateparser (==1.0.0)
Requires-Dist: device-detector (==0.10)
Requires-Dist: dotty-dict (==1.3.0)
Requires-Dist: elasticsearch (==7.13.4)
Requires-Dist: fastapi (==0.65.2)
Requires-Dist: h11 (==0.12.0)
Requires-Dist: idna (==3.2)
Requires-Dist: lark (==0.11.3)
Requires-Dist: multidict (==5.1.0)
Requires-Dist: numpy (==1.20.3)
Requires-Dist: prodict (==0.8.18)
Requires-Dist: pydantic (==1.8.2)
Requires-Dist: python-dateutil (==2.8.2)
Requires-Dist: python-multipart (==0.0.5)
Requires-Dist: pytz (==2021.1)
Requires-Dist: PyYAML (==5.4.1)
Requires-Dist: regex (==2021.7.6)
Requires-Dist: setuptools-scm (==6.0.1)
Requires-Dist: six (==1.16.0)
Requires-Dist: starlette (==0.14.2)
Requires-Dist: tracardi-graph-runner (==0.4.32)
Requires-Dist: tracardi-plugin-sdk (==0.1.25)
Requires-Dist: typing-extensions (==3.10.0.0)
Requires-Dist: tzlocal (==2.1)
Requires-Dist: urllib3 (==1.26.6)
Requires-Dist: uvicorn (==0.14.0)
Requires-Dist: xlrd (==2.0.1)
Requires-Dist: yarl (==1.6.3)
